<?xml version="1.0" encoding="UTF-8"?>
<sketch id="5dd8ade3-404d-4155-946a-4facd0cfd130" type="SRL">
    <point id="59233030-0bef-4637-a166-ef40b8277c2f" pressure="0.0"
        tilt_x="0.0" tilt_y="0.0" time="1177533194121" x="452.0" y="444.0"/>
    <point id="9555fa2b-dda3-4517-91b1-593b30b91794" pressure="0.0"
        tilt_x="0.0" tilt_y="0.0" time="1177533194137" x="452.0" y="441.0"/>
    <point id="bc727c15-bcc8-423e-ae51-b356649180b6" pressure="0.0"
        tilt_x="0.0" tilt_y="0.0" time="1177533194137" x="452.0" y="442.0"/>
    <point id="175f825a-7e94-474e-8a51-f03d02b1bf8b" pressure="0.0"
        tilt_x="0.0" tilt_y="0.0" time="1177533194152" x="451.0" y="439.0"/>
    <point id="b0f5644a-5212-49f3-92cc-3674094c151a" pressure="0.0"
        tilt_x="0.0" tilt_y="0.0" time="1177533194152" x="451.0" y="440.0"/>
    <point id="5c5db703-48c8-477b-be53-5aa3c95aa3eb" pressure="0.0"
        tilt_x="0.0" tilt_y="0.0" time="1177533194168" x="450.0" y="434.0"/>
    <point id="7c400cf4-93b0-4241-8bdd-b5e0c47151a6" pressure="0.0"
        tilt_x="0.0" tilt_y="0.0" time="1177533194168" x="450.0" y="437.0"/>
    <point id="ea7fa357-eb28-437d-ac78-defaaa35c343" pressure="0.0"
        tilt_x="0.0" tilt_y="0.0" time="1177533194183" x="450.0" y="429.0"/>
    <point id="17480599-a1bb-4047-8c3c-6aab523e348a" pressure="0.0"
        tilt_x="0.0" tilt_y="0.0" time="1177533194183" x="450.0" y="432.0"/>
    <point id="2b2d3413-7c0d-4737-abc2-08121368ab66" pressure="0.0"
        tilt_x="0.0" tilt_y="0.0" time="1177533194199" x="450.0" y="425.0"/>
    <point id="c101e9bb-d308-436b-984f-05ea40c1bc54" pressure="0.0"
        tilt_x="0.0" tilt_y="0.0" time="1177533194215" x="450.0" y="417.0"/>
    <point id="ff137dcd-2396-4236-873c-f37ca36c00ea" pressure="0.0"
        tilt_x="0.0" tilt_y="0.0" time="1177533194215" x="450.0" y="421.0"/>
    <point id="1f7131b6-9da7-4702-a5c4-84ac5b777a67" pressure="0.0"
        tilt_x="0.0" tilt_y="0.0" time="1177533194230" x="450.0" y="413.0"/>
    <point id="a320a048-13b8-494f-a9f1-561137f0f377" pressure="0.0"
        tilt_x="0.0" tilt_y="0.0" time="1177533194246" x="450.0" y="405.0"/>
    <point id="421c3c67-b869-4b39-ad5e-f7c74bbd18fc" pressure="0.0"
        tilt_x="0.0" tilt_y="0.0" time="1177533194246" x="450.0" y="409.0"/>
    <point id="9915995d-c866-475a-a25b-cc6b958821f6" pressure="0.0"
        tilt_x="0.0" tilt_y="0.0" time="1177533194262" x="450.0" y="395.0"/>
    <point id="500b15b0-98bd-404c-a8d1-70ac43cb6615" pressure="0.0"
        tilt_x="0.0" tilt_y="0.0" time="1177533194262" x="450.0" y="400.0"/>
    <point id="af00ee20-89f1-4497-b72e-aa3489181cfb" pressure="0.0"
        tilt_x="0.0" tilt_y="0.0" time="1177533194277" x="450.0" y="384.0"/>
    <point id="5d23a2d1-3ab0-4f14-9a54-310e76a23dff" pressure="0.0"
        tilt_x="0.0" tilt_y="0.0" time="1177533194277" x="450.0" y="389.0"/>
    <point id="d25c000a-9db9-4977-9b0b-18f63c64a31e" pressure="0.0"
        tilt_x="0.0" tilt_y="0.0" time="1177533194293" x="449.0" y="371.0"/>
    <point id="65a6b2f8-d560-4ffa-b5b3-1364a4604640" pressure="0.0"
        tilt_x="0.0" tilt_y="0.0" time="1177533194293" x="450.0" y="378.0"/>
    <point id="22e317b6-780d-4900-8ae6-655c2b900525" pressure="0.0"
        tilt_x="0.0" tilt_y="0.0" time="1177533194308" x="449.0" y="365.0"/>
    <point id="b644f7c0-988f-4fb3-a3e0-2ede8dbd6caa" pressure="0.0"
        tilt_x="0.0" tilt_y="0.0" time="1177533194324" x="449.0" y="354.0"/>
    <point id="f1e31003-a412-4ef4-acee-d6f52701c466" pressure="0.0"
        tilt_x="0.0" tilt_y="0.0" time="1177533194324" x="449.0" y="359.0"/>
    <point id="7197450e-4577-4e6f-8094-19fde5d062e4" pressure="0.0"
        tilt_x="0.0" tilt_y="0.0" time="1177533194340" x="448.0" y="345.0"/>
    <point id="2a644213-6e7b-4cc2-ad0e-6bbe4c7381e7" pressure="0.0"
        tilt_x="0.0" tilt_y="0.0" time="1177533194340" x="449.0" y="349.0"/>
    <point id="08862b18-bd50-4991-9522-05d2492bf7bf" pressure="0.0"
        tilt_x="0.0" tilt_y="0.0" time="1177533194355" x="448.0" y="337.0"/>
    <point id="9b76811c-6cba-4f83-bc96-2c6fc106230b" pressure="0.0"
        tilt_x="0.0" tilt_y="0.0" time="1177533194355" x="448.0" y="341.0"/>
    <point id="6380bff8-4155-498c-b1ec-157003d9cfcd" pressure="0.0"
        tilt_x="0.0" tilt_y="0.0" time="1177533194371" x="448.0" y="333.0"/>
    <point id="6455021f-c44a-463f-a42d-cdabd42f30f2" pressure="0.0"
        tilt_x="0.0" tilt_y="0.0" time="1177533194387" x="448.0" y="323.0"/>
    <point id="837085cb-5de5-4854-a645-81710f80b5ce" pressure="0.0"
        tilt_x="0.0" tilt_y="0.0" time="1177533194387" x="448.0" y="328.0"/>
    <point id="6ebd13b7-46ed-4e82-923d-4df7527953b8" pressure="0.0"
        tilt_x="0.0" tilt_y="0.0" time="1177533194402" x="448.0" y="318.0"/>
    <point id="47cbb2b9-8bc8-4031-9e66-f3139b08d48e" pressure="0.0"
        tilt_x="0.0" tilt_y="0.0" time="1177533194402" x="449.0" y="313.0"/>
    <point id="209f1e11-675e-49a4-99af-ad350c91e74c" pressure="0.0"
        tilt_x="0.0" tilt_y="0.0" time="1177533194418" x="450.0" y="305.0"/>
    <point id="c56b1045-954d-4961-8fbd-0579b19b255b" pressure="0.0"
        tilt_x="0.0" tilt_y="0.0" time="1177533194418" x="450.0" y="309.0"/>
    <point id="e4ec8a68-da8e-49a9-a812-ff4b0ba6e52d" pressure="0.0"
        tilt_x="0.0" tilt_y="0.0" time="1177533194433" x="451.0" y="302.0"/>
    <point id="5b3771b8-e60f-4bd6-937f-bde4ded356e0" pressure="0.0"
        tilt_x="0.0" tilt_y="0.0" time="1177533194449" x="451.0" y="299.0"/>
    <point id="dc8f269d-a2f9-471c-b847-8c95d179dc3d" pressure="0.0"
        tilt_x="0.0" tilt_y="0.0" time="1177533194449" x="451.0" y="300.0"/>
    <point id="29ccb5e9-fafd-4575-9823-2bac3f7cfbd7" pressure="0.0"
        tilt_x="0.0" tilt_y="0.0" time="1177533194465" x="451.0" y="297.0"/>
    <point id="6c5ac126-0907-48e3-b16a-d68c0defa4b4" pressure="0.0"
        tilt_x="0.0" tilt_y="0.0" time="1177533194465" x="452.0" y="296.0"/>
    <point id="b3ec50f1-895c-49f9-af11-519ad205adf2" pressure="0.0"
        tilt_x="0.0" tilt_y="0.0" time="1177533194480" x="452.0" y="294.0"/>
    <point id="0b6c220a-fbee-4b9b-b5d4-3ba6a9066953" pressure="0.0"
        tilt_x="0.0" tilt_y="0.0" time="1177533194480" x="452.0" y="295.0"/>
    <point id="7793dd1b-098b-4a64-a8b2-eef1d0b57533" pressure="0.0"
        tilt_x="0.0" tilt_y="0.0" time="1177533194558" x="451.0" y="294.0"/>
    <point id="3650feca-6dbf-425b-b8bf-7667b59ea548" pressure="0.0"
        tilt_x="0.0" tilt_y="0.0" time="1177533194558" x="452.0" y="294.0"/>
    <point id="1f6c6b20-b692-4762-bb0f-9c129ae0f4f2" pressure="0.0"
        tilt_x="0.0" tilt_y="0.0" time="1177533194605" x="451.0" y="294.0"/>
    <point id="3290d57b-6009-4b60-804d-d195c86d500b" pressure="0.0"
        tilt_x="0.0" tilt_y="0.0" time="1177533194699" x="450.0" y="294.0"/>
    <point id="7f0925a1-1213-403f-82f6-c0abf8efb6e9" pressure="0.0"
        tilt_x="0.0" tilt_y="0.0" time="1177533194762" x="449.0" y="294.0"/>
    <point id="349412b9-272d-4629-a22d-de791b2d82dd" pressure="0.0"
        tilt_x="0.0" tilt_y="0.0" time="1177533194777" x="449.0" y="293.0"/>
    <point id="5c894800-0199-4f64-86da-d2ec70e6b462" pressure="0.0"
        tilt_x="0.0" tilt_y="0.0" time="1177533194793" x="448.0" y="291.0"/>
    <point id="13c38349-7d0a-4be4-ae57-79be6ca94445" pressure="0.0"
        tilt_x="0.0" tilt_y="0.0" time="1177533194793" x="448.0" y="292.0"/>
    <point id="03c19a76-3d9c-45f9-9ced-a505c009dab2" pressure="0.0"
        tilt_x="0.0" tilt_y="0.0" time="1177533194808" x="448.0" y="290.0"/>
    <point id="463a63c8-ce0f-4ebb-9d05-7172e484bb2e" pressure="0.0"
        tilt_x="0.0" tilt_y="0.0" time="1177533194824" x="447.0" y="287.0"/>
    <point id="a9eefed2-28b4-4da4-8756-d2b8ebe28da6" pressure="0.0"
        tilt_x="0.0" tilt_y="0.0" time="1177533194824" x="447.0" y="288.0"/>
    <point id="35471bbb-8523-4deb-9193-26b360d81897" pressure="0.0"
        tilt_x="0.0" tilt_y="0.0" time="1177533194840" x="445.0" y="282.0"/>
    <point id="6bcdd332-f1a9-4a21-b01b-e113965560b6" pressure="0.0"
        tilt_x="0.0" tilt_y="0.0" time="1177533194840" x="446.0" y="285.0"/>
    <point id="12299899-699a-4e98-8546-c5e3f7208a1f" pressure="0.0"
        tilt_x="0.0" tilt_y="0.0" time="1177533194855" x="445.0" y="279.0"/>
    <point id="11facfcd-12b9-40a5-8cdb-51547ba849a7" pressure="0.0"
        tilt_x="0.0" tilt_y="0.0" time="1177533194871" x="444.0" y="272.0"/>
    <point id="41b99f03-f788-4122-9302-1ae53f7ec053" pressure="0.0"
        tilt_x="0.0" tilt_y="0.0" time="1177533194871" x="444.0" y="276.0"/>
    <point id="427cdd8a-4d87-4c36-b4de-75fccbe8598d" pressure="0.0"
        tilt_x="0.0" tilt_y="0.0" time="1177533194887" x="443.0" y="265.0"/>
    <point id="92879bde-b2f6-4bd2-8286-b984f716ba50" pressure="0.0"
        tilt_x="0.0" tilt_y="0.0" time="1177533194887" x="443.0" y="269.0"/>
    <point id="bbde8f82-d4d2-4bd4-a987-ab10daea6aa4" pressure="0.0"
        tilt_x="0.0" tilt_y="0.0" time="1177533194902" x="443.0" y="257.0"/>
    <point id="0f27b31f-72f7-4ac1-9b55-9994afaf4c4d" pressure="0.0"
        tilt_x="0.0" tilt_y="0.0" time="1177533194902" x="443.0" y="261.0"/>
    <point id="71f044a7-2e0c-4926-8e24-d227017fa71c" pressure="0.0"
        tilt_x="0.0" tilt_y="0.0" time="1177533194918" x="444.0" y="254.0"/>
    <point id="3a3969db-2162-41f3-a150-19f54b620826" pressure="0.0"
        tilt_x="0.0" tilt_y="0.0" time="1177533194918" x="445.0" y="249.0"/>
    <point id="389093b1-d5af-4491-9d5c-321719e03ca2" pressure="0.0"
        tilt_x="0.0" tilt_y="0.0" time="1177533194933" x="446.0" y="245.0"/>
    <point id="6a9759f3-3168-4d8d-8ef7-53f9e082095b" pressure="0.0"
        tilt_x="0.0" tilt_y="0.0" time="1177533194949" x="447.0" y="241.0"/>
    <point id="c81cd4a9-a075-4b42-96c3-53217431ade7" pressure="0.0"
        tilt_x="0.0" tilt_y="0.0" time="1177533194949" x="448.0" y="236.0"/>
    <point id="4ccf2da6-d11b-496f-b073-1d9684337bb1" pressure="0.0"
        tilt_x="0.0" tilt_y="0.0" time="1177533194965" x="450.0" y="232.0"/>
    <point id="9e6930b2-63ee-468c-a38e-6e46d9ecffac" pressure="0.0"
        tilt_x="0.0" tilt_y="0.0" time="1177533194965" x="452.0" y="228.0"/>
    <point id="4dc96577-53f4-4ecd-a03d-0b29d28a45d4" pressure="0.0"
        tilt_x="0.0" tilt_y="0.0" time="1177533194980" x="454.0" y="224.0"/>
    <point id="41e27f08-c7ae-4ba3-8fa9-b05d886e7aa3" pressure="0.0"
        tilt_x="0.0" tilt_y="0.0" time="1177533194980" x="457.0" y="220.0"/>
    <point id="cbfc1696-f7e6-4dc7-8d6e-07d6406b5ed6" pressure="0.0"
        tilt_x="0.0" tilt_y="0.0" time="1177533194996" x="459.0" y="217.0"/>
    <point id="a0301eaf-86b1-447a-bb77-44f772464f6a" pressure="0.0"
        tilt_x="0.0" tilt_y="0.0" time="1177533194996" x="461.0" y="213.0"/>
    <point id="62d881b6-be79-49e2-b693-482108a24cb3" pressure="0.0"
        tilt_x="0.0" tilt_y="0.0" time="1177533195012" x="463.0" y="211.0"/>
    <point id="5ef10c8e-cacd-490b-a0c2-69856eb56153" pressure="0.0"
        tilt_x="0.0" tilt_y="0.0" time="1177533195027" x="465.0" y="208.0"/>
    <point id="11d1e813-d6ab-4f44-a185-4e65f972ed3f" pressure="0.0"
        tilt_x="0.0" tilt_y="0.0" time="1177533195027" x="467.0" y="206.0"/>
    <point id="8250b85c-a231-44b2-8309-6f54a8b4e757" pressure="0.0"
        tilt_x="0.0" tilt_y="0.0" time="1177533195043" x="469.0" y="204.0"/>
    <point id="26f3d1f6-b8bb-4c9c-848d-887d950fc9e1" pressure="0.0"
        tilt_x="0.0" tilt_y="0.0" time="1177533195058" x="472.0" y="203.0"/>
    <point id="c49bfafb-6d0b-4d0b-b457-16a03803b475" pressure="0.0"
        tilt_x="0.0" tilt_y="0.0" time="1177533195058" x="474.0" y="201.0"/>
    <point id="3ddbad71-3fb2-423c-b5e7-3af207d01f0a" pressure="0.0"
        tilt_x="0.0" tilt_y="0.0" time="1177533195074" x="477.0" y="200.0"/>
    <point id="9d43db36-80fd-45b9-9ed0-554f9b8b642c" pressure="0.0"
        tilt_x="0.0" tilt_y="0.0" time="1177533195074" x="480.0" y="199.0"/>
    <point id="e6393efb-4427-4b20-8cc9-ad6433661123" pressure="0.0"
        tilt_x="0.0" tilt_y="0.0" time="1177533195090" x="483.0" y="198.0"/>
    <point id="aade96bb-1e08-4618-ab78-78fad27ef0a3" pressure="0.0"
        tilt_x="0.0" tilt_y="0.0" time="1177533195090" x="487.0" y="197.0"/>
    <point id="3870807c-819d-4803-bdd7-cd4dce7ea156" pressure="0.0"
        tilt_x="0.0" tilt_y="0.0" time="1177533195105" x="491.0" y="196.0"/>
    <point id="bf9dc10d-68ee-4fd7-9b7c-c9e65500c691" pressure="0.0"
        tilt_x="0.0" tilt_y="0.0" time="1177533195105" x="496.0" y="195.0"/>
    <point id="b7aa29c5-3a27-4d27-a334-bc4b46e835bb" pressure="0.0"
        tilt_x="0.0" tilt_y="0.0" time="1177533195121" x="500.0" y="194.0"/>
    <point id="300e07e6-2d88-4f3d-b7c9-7cd3d412f46c" pressure="0.0"
        tilt_x="0.0" tilt_y="0.0" time="1177533195137" x="505.0" y="194.0"/>
    <point id="36189c6a-6e2e-45f6-9f50-37166ea8705f" pressure="0.0"
        tilt_x="0.0" tilt_y="0.0" time="1177533195137" x="509.0" y="193.0"/>
    <point id="0c4ab4bf-76e4-4207-bf7e-829a4c179290" pressure="0.0"
        tilt_x="0.0" tilt_y="0.0" time="1177533195152" x="514.0" y="193.0"/>
    <point id="2a6fc509-fba1-4296-9011-2823cfa85e74" pressure="0.0"
        tilt_x="0.0" tilt_y="0.0" time="1177533195152" x="518.0" y="193.0"/>
    <point id="0a547036-a933-424e-9df1-3cfe0c2622ec" pressure="0.0"
        tilt_x="0.0" tilt_y="0.0" time="1177533195168" x="522.0" y="193.0"/>
    <point id="9b9a5e78-2f7e-49b3-9239-c1fadf1b732f" pressure="0.0"
        tilt_x="0.0" tilt_y="0.0" time="1177533195168" x="526.0" y="194.0"/>
    <point id="a12bf721-8b93-4501-a0f7-4530fa5258a7" pressure="0.0"
        tilt_x="0.0" tilt_y="0.0" time="1177533195183" x="531.0" y="195.0"/>
    <point id="1e8b7f0d-47ea-4dab-bcc4-26105922a844" pressure="0.0"
        tilt_x="0.0" tilt_y="0.0" time="1177533195183" x="535.0" y="197.0"/>
    <point id="87d3c6f7-79b6-47ab-95ad-5d7c0daffa8d" pressure="0.0"
        tilt_x="0.0" tilt_y="0.0" time="1177533195199" x="539.0" y="200.0"/>
    <point id="64ae256f-e736-4486-8db8-183e0c55edaa" pressure="0.0"
        tilt_x="0.0" tilt_y="0.0" time="1177533195215" x="542.0" y="204.0"/>
    <point id="2add54c8-5fa3-4f99-9979-2fd73569a42d" pressure="0.0"
        tilt_x="0.0" tilt_y="0.0" time="1177533195215" x="546.0" y="209.0"/>
    <point id="1a376e7e-a376-44fc-9880-59b8901eeba5" pressure="0.0"
        tilt_x="0.0" tilt_y="0.0" time="1177533195230" x="549.0" y="215.0"/>
    <point id="5d0f4b2c-7ab8-4dc6-9098-d7f7a0191c2e" pressure="0.0"
        tilt_x="0.0" tilt_y="0.0" time="1177533195230" x="551.0" y="220.0"/>
    <point id="ae55e8d9-639d-44d8-8c8c-e0a5c683b6b0" pressure="0.0"
        tilt_x="0.0" tilt_y="0.0" time="1177533195246" x="554.0" y="224.0"/>
    <point id="f4636183-5dbe-42f2-8559-0b5f80d6807e" pressure="0.0"
        tilt_x="0.0" tilt_y="0.0" time="1177533195262" x="556.0" y="227.0"/>
    <point id="ee0d77e8-e07a-4ddb-9e9a-18a7d83a29ac" pressure="0.0"
        tilt_x="0.0" tilt_y="0.0" time="1177533195262" x="558.0" y="229.0"/>
    <point id="5b22067b-9f6a-45ca-89d3-b309567baec9" pressure="0.0"
        tilt_x="0.0" tilt_y="0.0" time="1177533195277" x="561.0" y="230.0"/>
    <point id="bd9d5347-ef37-48c0-ae33-c985ac5f02fe" pressure="0.0"
        tilt_x="0.0" tilt_y="0.0" time="1177533195277" x="563.0" y="232.0"/>
    <point id="f6609944-2187-4758-b842-7ebc1d7852d0" pressure="0.0"
        tilt_x="0.0" tilt_y="0.0" time="1177533195293" x="565.0" y="233.0"/>
    <point id="ea30b7be-da61-4b95-816d-91a680c19d2c" pressure="0.0"
        tilt_x="0.0" tilt_y="0.0" time="1177533195293" x="566.0" y="234.0"/>
    <stroke id="6cf36470-b529-4ad8-b94f-aeb964a2fe98" label="Complex" visible="true">
        <arg type="point">59233030-0bef-4637-a166-ef40b8277c2f</arg>
        <arg type="point">bc727c15-bcc8-423e-ae51-b356649180b6</arg>
        <arg type="point">9555fa2b-dda3-4517-91b1-593b30b91794</arg>
        <arg type="point">b0f5644a-5212-49f3-92cc-3674094c151a</arg>
        <arg type="point">175f825a-7e94-474e-8a51-f03d02b1bf8b</arg>
        <arg type="point">7c400cf4-93b0-4241-8bdd-b5e0c47151a6</arg>
        <arg type="point">5c5db703-48c8-477b-be53-5aa3c95aa3eb</arg>
        <arg type="point">17480599-a1bb-4047-8c3c-6aab523e348a</arg>
        <arg type="point">ea7fa357-eb28-437d-ac78-defaaa35c343</arg>
        <arg type="point">2b2d3413-7c0d-4737-abc2-08121368ab66</arg>
        <arg type="point">ff137dcd-2396-4236-873c-f37ca36c00ea</arg>
        <arg type="point">c101e9bb-d308-436b-984f-05ea40c1bc54</arg>
        <arg type="point">1f7131b6-9da7-4702-a5c4-84ac5b777a67</arg>
        <arg type="point">421c3c67-b869-4b39-ad5e-f7c74bbd18fc</arg>
        <arg type="point">a320a048-13b8-494f-a9f1-561137f0f377</arg>
        <arg type="point">500b15b0-98bd-404c-a8d1-70ac43cb6615</arg>
        <arg type="point">9915995d-c866-475a-a25b-cc6b958821f6</arg>
        <arg type="point">5d23a2d1-3ab0-4f14-9a54-310e76a23dff</arg>
        <arg type="point">af00ee20-89f1-4497-b72e-aa3489181cfb</arg>
        <arg type="point">65a6b2f8-d560-4ffa-b5b3-1364a4604640</arg>
        <arg type="point">d25c000a-9db9-4977-9b0b-18f63c64a31e</arg>
        <arg type="point">22e317b6-780d-4900-8ae6-655c2b900525</arg>
        <arg type="point">f1e31003-a412-4ef4-acee-d6f52701c466</arg>
        <arg type="point">b644f7c0-988f-4fb3-a3e0-2ede8dbd6caa</arg>
        <arg type="point">2a644213-6e7b-4cc2-ad0e-6bbe4c7381e7</arg>
        <arg type="point">7197450e-4577-4e6f-8094-19fde5d062e4</arg>
        <arg type="point">9b76811c-6cba-4f83-bc96-2c6fc106230b</arg>
        <arg type="point">08862b18-bd50-4991-9522-05d2492bf7bf</arg>
        <arg type="point">6380bff8-4155-498c-b1ec-157003d9cfcd</arg>
        <arg type="point">837085cb-5de5-4854-a645-81710f80b5ce</arg>
        <arg type="point">6455021f-c44a-463f-a42d-cdabd42f30f2</arg>
        <arg type="point">6ebd13b7-46ed-4e82-923d-4df7527953b8</arg>
        <arg type="point">47cbb2b9-8bc8-4031-9e66-f3139b08d48e</arg>
        <arg type="point">c56b1045-954d-4961-8fbd-0579b19b255b</arg>
        <arg type="point">209f1e11-675e-49a4-99af-ad350c91e74c</arg>
        <arg type="point">e4ec8a68-da8e-49a9-a812-ff4b0ba6e52d</arg>
        <arg type="point">dc8f269d-a2f9-471c-b847-8c95d179dc3d</arg>
        <arg type="point">5b3771b8-e60f-4bd6-937f-bde4ded356e0</arg>
        <arg type="point">29ccb5e9-fafd-4575-9823-2bac3f7cfbd7</arg>
        <arg type="point">6c5ac126-0907-48e3-b16a-d68c0defa4b4</arg>
        <arg type="point">0b6c220a-fbee-4b9b-b5d4-3ba6a9066953</arg>
        <arg type="point">b3ec50f1-895c-49f9-af11-519ad205adf2</arg>
        <arg type="point">7793dd1b-098b-4a64-a8b2-eef1d0b57533</arg>
        <arg type="point">3650feca-6dbf-425b-b8bf-7667b59ea548</arg>
        <arg type="point">1f6c6b20-b692-4762-bb0f-9c129ae0f4f2</arg>
        <arg type="point">3290d57b-6009-4b60-804d-d195c86d500b</arg>
        <arg type="point">7f0925a1-1213-403f-82f6-c0abf8efb6e9</arg>
        <arg type="point">349412b9-272d-4629-a22d-de791b2d82dd</arg>
        <arg type="point">13c38349-7d0a-4be4-ae57-79be6ca94445</arg>
        <arg type="point">5c894800-0199-4f64-86da-d2ec70e6b462</arg>
        <arg type="point">03c19a76-3d9c-45f9-9ced-a505c009dab2</arg>
        <arg type="point">a9eefed2-28b4-4da4-8756-d2b8ebe28da6</arg>
        <arg type="point">463a63c8-ce0f-4ebb-9d05-7172e484bb2e</arg>
        <arg type="point">6bcdd332-f1a9-4a21-b01b-e113965560b6</arg>
        <arg type="point">35471bbb-8523-4deb-9193-26b360d81897</arg>
        <arg type="point">12299899-699a-4e98-8546-c5e3f7208a1f</arg>
        <arg type="point">41b99f03-f788-4122-9302-1ae53f7ec053</arg>
        <arg type="point">11facfcd-12b9-40a5-8cdb-51547ba849a7</arg>
        <arg type="point">92879bde-b2f6-4bd2-8286-b984f716ba50</arg>
        <arg type="point">427cdd8a-4d87-4c36-b4de-75fccbe8598d</arg>
        <arg type="point">0f27b31f-72f7-4ac1-9b55-9994afaf4c4d</arg>
        <arg type="point">bbde8f82-d4d2-4bd4-a987-ab10daea6aa4</arg>
        <arg type="point">71f044a7-2e0c-4926-8e24-d227017fa71c</arg>
        <arg type="point">3a3969db-2162-41f3-a150-19f54b620826</arg>
        <arg type="point">389093b1-d5af-4491-9d5c-321719e03ca2</arg>
        <arg type="point">6a9759f3-3168-4d8d-8ef7-53f9e082095b</arg>
        <arg type="point">c81cd4a9-a075-4b42-96c3-53217431ade7</arg>
        <arg type="point">4ccf2da6-d11b-496f-b073-1d9684337bb1</arg>
        <arg type="point">9e6930b2-63ee-468c-a38e-6e46d9ecffac</arg>
        <arg type="point">4dc96577-53f4-4ecd-a03d-0b29d28a45d4</arg>
        <arg type="point">41e27f08-c7ae-4ba3-8fa9-b05d886e7aa3</arg>
        <arg type="point">cbfc1696-f7e6-4dc7-8d6e-07d6406b5ed6</arg>
        <arg type="point">a0301eaf-86b1-447a-bb77-44f772464f6a</arg>
        <arg type="point">62d881b6-be79-49e2-b693-482108a24cb3</arg>
        <arg type="point">5ef10c8e-cacd-490b-a0c2-69856eb56153</arg>
        <arg type="point">11d1e813-d6ab-4f44-a185-4e65f972ed3f</arg>
        <arg type="point">8250b85c-a231-44b2-8309-6f54a8b4e757</arg>
        <arg type="point">26f3d1f6-b8bb-4c9c-848d-887d950fc9e1</arg>
        <arg type="point">c49bfafb-6d0b-4d0b-b457-16a03803b475</arg>
        <arg type="point">3ddbad71-3fb2-423c-b5e7-3af207d01f0a</arg>
        <arg type="point">9d43db36-80fd-45b9-9ed0-554f9b8b642c</arg>
        <arg type="point">e6393efb-4427-4b20-8cc9-ad6433661123</arg>
        <arg type="point">aade96bb-1e08-4618-ab78-78fad27ef0a3</arg>
        <arg type="point">3870807c-819d-4803-bdd7-cd4dce7ea156</arg>
        <arg type="point">bf9dc10d-68ee-4fd7-9b7c-c9e65500c691</arg>
        <arg type="point">b7aa29c5-3a27-4d27-a334-bc4b46e835bb</arg>
        <arg type="point">300e07e6-2d88-4f3d-b7c9-7cd3d412f46c</arg>
        <arg type="point">36189c6a-6e2e-45f6-9f50-37166ea8705f</arg>
        <arg type="point">0c4ab4bf-76e4-4207-bf7e-829a4c179290</arg>
        <arg type="point">2a6fc509-fba1-4296-9011-2823cfa85e74</arg>
        <arg type="point">0a547036-a933-424e-9df1-3cfe0c2622ec</arg>
        <arg type="point">9b9a5e78-2f7e-49b3-9239-c1fadf1b732f</arg>
        <arg type="point">a12bf721-8b93-4501-a0f7-4530fa5258a7</arg>
        <arg type="point">1e8b7f0d-47ea-4dab-bcc4-26105922a844</arg>
        <arg type="point">87d3c6f7-79b6-47ab-95ad-5d7c0daffa8d</arg>
        <arg type="point">64ae256f-e736-4486-8db8-183e0c55edaa</arg>
        <arg type="point">2add54c8-5fa3-4f99-9979-2fd73569a42d</arg>
        <arg type="point">1a376e7e-a376-44fc-9880-59b8901eeba5</arg>
        <arg type="point">5d0f4b2c-7ab8-4dc6-9098-d7f7a0191c2e</arg>
        <arg type="point">ae55e8d9-639d-44d8-8c8c-e0a5c683b6b0</arg>
        <arg type="point">f4636183-5dbe-42f2-8559-0b5f80d6807e</arg>
        <arg type="point">ee0d77e8-e07a-4ddb-9e9a-18a7d83a29ac</arg>
        <arg type="point">5b22067b-9f6a-45ca-89d3-b309567baec9</arg>
        <arg type="point">bd9d5347-ef37-48c0-ae33-c985ac5f02fe</arg>
        <arg type="point">f6609944-2187-4758-b842-7ebc1d7852d0</arg>
        <arg type="point">ea30b7be-da61-4b95-816d-91a680c19d2c</arg>
    </stroke>
</sketch>
