<?xml version="1.0" encoding="UTF-8"?>
<sketch id="0dda5168-92ab-41ec-92cc-b246478da44c" type="SRL">
    <point id="bd58b928-983f-4dba-91d6-cacff471ceef" pressure="0.0"
        tilt_x="0.0" tilt_y="0.0" time="1177532754368" x="222.0" y="332.0"/>
    <point id="b6c1c7ff-f7ea-438a-95d8-f23459d03b18" pressure="0.0"
        tilt_x="0.0" tilt_y="0.0" time="1177532754384" x="220.0" y="332.0"/>
    <point id="241e6f0c-2064-4de4-adcf-9245dd2759c0" pressure="0.0"
        tilt_x="0.0" tilt_y="0.0" time="1177532754384" x="221.0" y="332.0"/>
    <point id="efaa0dc0-77dd-4c30-be9a-1e1330c20d0a" pressure="0.0"
        tilt_x="0.0" tilt_y="0.0" time="1177532754446" x="221.0" y="331.0"/>
    <point id="bef89d23-d679-43a6-9c4a-837c03fa4a36" pressure="0.0"
        tilt_x="0.0" tilt_y="0.0" time="1177532754446" x="221.0" y="332.0"/>
    <point id="3889d5a7-51cb-4751-81ee-e413f0359146" pressure="0.0"
        tilt_x="0.0" tilt_y="0.0" time="1177532754462" x="222.0" y="331.0"/>
    <point id="08372411-5a63-4f1d-85a7-16d18f72fb9b" pressure="0.0"
        tilt_x="0.0" tilt_y="0.0" time="1177532754462" x="223.0" y="331.0"/>
    <point id="ce8ce067-d149-45f3-a398-1c133ba65e80" pressure="0.0"
        tilt_x="0.0" tilt_y="0.0" time="1177532754478" x="224.0" y="330.0"/>
    <point id="60fd5f26-e2f2-450c-8a1b-04101159ca45" pressure="0.0"
        tilt_x="0.0" tilt_y="0.0" time="1177532754478" x="226.0" y="329.0"/>
    <point id="093dac45-57ff-4ea3-b059-aa5b77f5efaf" pressure="0.0"
        tilt_x="0.0" tilt_y="0.0" time="1177532754493" x="228.0" y="329.0"/>
    <point id="c0fbe4a1-6dac-4af2-a500-87a2f2d55432" pressure="0.0"
        tilt_x="0.0" tilt_y="0.0" time="1177532754509" x="231.0" y="328.0"/>
    <point id="6bc639ab-9108-47f4-97ff-c21d96e56663" pressure="0.0"
        tilt_x="0.0" tilt_y="0.0" time="1177532754509" x="234.0" y="326.0"/>
    <point id="f787b360-904a-464c-8057-fac5258f97ab" pressure="0.0"
        tilt_x="0.0" tilt_y="0.0" time="1177532754524" x="238.0" y="325.0"/>
    <point id="dc8eab5a-fdab-46a1-ac94-f4b6552d7d22" pressure="0.0"
        tilt_x="0.0" tilt_y="0.0" time="1177532754524" x="243.0" y="323.0"/>
    <point id="95285c39-0baf-4339-87dd-afc53defaad7" pressure="0.0"
        tilt_x="0.0" tilt_y="0.0" time="1177532754540" x="248.0" y="321.0"/>
    <point id="a59f43a4-8599-4073-bd2e-fb5c52659c19" pressure="0.0"
        tilt_x="0.0" tilt_y="0.0" time="1177532754540" x="253.0" y="319.0"/>
    <point id="0409627e-0daa-4973-9cf3-68dd5c0ff1c9" pressure="0.0"
        tilt_x="0.0" tilt_y="0.0" time="1177532754556" x="259.0" y="317.0"/>
    <point id="0e30579d-ffe6-4023-9a61-55798a5e9b33" pressure="0.0"
        tilt_x="0.0" tilt_y="0.0" time="1177532754571" x="266.0" y="314.0"/>
    <point id="cf92a225-cd93-4d23-97d2-5687933ee32a" pressure="0.0"
        tilt_x="0.0" tilt_y="0.0" time="1177532754571" x="273.0" y="312.0"/>
    <point id="5feaff76-3998-4644-ac4c-f0f785a0be7d" pressure="0.0"
        tilt_x="0.0" tilt_y="0.0" time="1177532754587" x="281.0" y="310.0"/>
    <point id="eb563912-ca64-4e06-ba44-93151469d11e" pressure="0.0"
        tilt_x="0.0" tilt_y="0.0" time="1177532754587" x="290.0" y="308.0"/>
    <point id="eb0398b3-3d70-4e11-ab5d-33b68642201e" pressure="0.0"
        tilt_x="0.0" tilt_y="0.0" time="1177532754603" x="298.0" y="306.0"/>
    <point id="fd2e1caa-504d-4e80-89b6-9c2af748e5f8" pressure="0.0"
        tilt_x="0.0" tilt_y="0.0" time="1177532754618" x="307.0" y="304.0"/>
    <point id="46c80363-bc60-40d8-a96a-bb09527b0c24" pressure="0.0"
        tilt_x="0.0" tilt_y="0.0" time="1177532754618" x="316.0" y="303.0"/>
    <point id="6320171a-dbe5-4a30-ba27-a22cc0ee4373" pressure="0.0"
        tilt_x="0.0" tilt_y="0.0" time="1177532754634" x="325.0" y="301.0"/>
    <point id="d4440982-5c17-4dc1-9dc2-c5f8cce2a625" pressure="0.0"
        tilt_x="0.0" tilt_y="0.0" time="1177532754634" x="333.0" y="299.0"/>
    <point id="acb10c7d-fb4b-4551-b197-044515544a6a" pressure="0.0"
        tilt_x="0.0" tilt_y="0.0" time="1177532754649" x="341.0" y="297.0"/>
    <point id="e9b2227f-07e3-4a5b-af2e-fb226426106a" pressure="0.0"
        tilt_x="0.0" tilt_y="0.0" time="1177532754649" x="348.0" y="296.0"/>
    <point id="5546ef2a-e041-4a1d-bc10-2ef8374ff482" pressure="0.0"
        tilt_x="0.0" tilt_y="0.0" time="1177532754665" x="354.0" y="295.0"/>
    <point id="f478814a-4120-4fc1-b1cb-63d9b9d5bc7d" pressure="0.0"
        tilt_x="0.0" tilt_y="0.0" time="1177532754665" x="360.0" y="294.0"/>
    <point id="c5e85a10-453e-4990-8502-e46e9af01c5b" pressure="0.0"
        tilt_x="0.0" tilt_y="0.0" time="1177532754681" x="365.0" y="293.0"/>
    <point id="5801ada9-e9b1-456a-9e95-3f7500b30b21" pressure="0.0"
        tilt_x="0.0" tilt_y="0.0" time="1177532754696" x="369.0" y="292.0"/>
    <point id="bdcd7bae-a265-4d9d-a24f-5e61f44deb36" pressure="0.0"
        tilt_x="0.0" tilt_y="0.0" time="1177532754696" x="372.0" y="291.0"/>
    <point id="4d0aa280-2a5f-4971-a232-9eddff985dff" pressure="0.0"
        tilt_x="0.0" tilt_y="0.0" time="1177532754712" x="375.0" y="291.0"/>
    <point id="45e3ca54-2e71-453c-af1f-000afd161129" pressure="0.0"
        tilt_x="0.0" tilt_y="0.0" time="1177532754712" x="377.0" y="290.0"/>
    <point id="d66f8375-d6d8-4451-a526-3ff80bcc94a2" pressure="0.0"
        tilt_x="0.0" tilt_y="0.0" time="1177532754728" x="378.0" y="290.0"/>
    <point id="eba538fd-5d7a-4db2-b910-8246603ea536" pressure="0.0"
        tilt_x="0.0" tilt_y="0.0" time="1177532754743" x="379.0" y="289.0"/>
    <point id="a6fbba50-f49c-40a9-b71f-df663617032e" pressure="0.0"
        tilt_x="0.0" tilt_y="0.0" time="1177532754759" x="378.0" y="289.0"/>
    <point id="f0374d34-1e22-4a22-94d0-11581af6976d" pressure="0.0"
        tilt_x="0.0" tilt_y="0.0" time="1177532754774" x="377.0" y="289.0"/>
    <point id="ec089bf3-dffd-45b4-8d66-b26176e190a8" pressure="0.0"
        tilt_x="0.0" tilt_y="0.0" time="1177532754837" x="377.0" y="288.0"/>
    <point id="b983fe3c-c525-4497-98b6-73d861a89618" pressure="0.0"
        tilt_x="0.0" tilt_y="0.0" time="1177532754853" x="376.0" y="286.0"/>
    <point id="7723f1fb-ba8f-4df4-818a-c8015ed0fb0a" pressure="0.0"
        tilt_x="0.0" tilt_y="0.0" time="1177532754853" x="376.0" y="287.0"/>
    <point id="6572729b-02cd-4ae1-bebb-254c811301f8" pressure="0.0"
        tilt_x="0.0" tilt_y="0.0" time="1177532754868" x="375.0" y="285.0"/>
    <point id="032c62b4-2719-4762-800d-e198cf74f5f0" pressure="0.0"
        tilt_x="0.0" tilt_y="0.0" time="1177532754884" x="372.0" y="281.0"/>
    <point id="ccf57056-d2ab-4e7a-b14f-c58e930f0efb" pressure="0.0"
        tilt_x="0.0" tilt_y="0.0" time="1177532754884" x="374.0" y="283.0"/>
    <point id="5b985c6d-4782-4e76-b89d-315b73e2e4ce" pressure="0.0"
        tilt_x="0.0" tilt_y="0.0" time="1177532754899" x="368.0" y="277.0"/>
    <point id="2664fd79-9ced-4465-b9f8-294881d8d939" pressure="0.0"
        tilt_x="0.0" tilt_y="0.0" time="1177532754899" x="371.0" y="279.0"/>
    <point id="b0fddc0d-8438-405e-a5ff-4a47b895d3c5" pressure="0.0"
        tilt_x="0.0" tilt_y="0.0" time="1177532754915" x="366.0" y="275.0"/>
    <point id="8a80e613-9163-4d9f-96cb-8b050b7bcfc9" pressure="0.0"
        tilt_x="0.0" tilt_y="0.0" time="1177532754931" x="359.0" y="270.0"/>
    <point id="e444ea9a-e2a9-4bbb-a97d-0fc30769a5df" pressure="0.0"
        tilt_x="0.0" tilt_y="0.0" time="1177532754931" x="362.0" y="272.0"/>
    <point id="e007a7a6-a073-4d8a-8214-f3c1803b6c2e" pressure="0.0"
        tilt_x="0.0" tilt_y="0.0" time="1177532754946" x="349.0" y="266.0"/>
    <point id="ee3fd76c-4cc4-42ac-99d4-455d4525c5bd" pressure="0.0"
        tilt_x="0.0" tilt_y="0.0" time="1177532754946" x="354.0" y="268.0"/>
    <point id="e056e479-db25-417e-a1e9-09b9e40b2496" pressure="0.0"
        tilt_x="0.0" tilt_y="0.0" time="1177532754962" x="339.0" y="264.0"/>
    <point id="dd823a99-54fe-4350-af7e-c10681ea6a86" pressure="0.0"
        tilt_x="0.0" tilt_y="0.0" time="1177532754962" x="344.0" y="265.0"/>
    <point id="bb9ad587-41e4-4933-9f9c-34a384bdcace" pressure="0.0"
        tilt_x="0.0" tilt_y="0.0" time="1177532754978" x="329.0" y="262.0"/>
    <point id="d453d253-e757-48f4-af98-7049fbaa1030" pressure="0.0"
        tilt_x="0.0" tilt_y="0.0" time="1177532754978" x="334.0" y="263.0"/>
    <point id="32fa8b92-a170-41e1-b753-2afdc605064a" pressure="0.0"
        tilt_x="0.0" tilt_y="0.0" time="1177532754993" x="324.0" y="262.0"/>
    <point id="f1ca70c1-8ab5-4de3-bf55-6f513faeeb80" pressure="0.0"
        tilt_x="0.0" tilt_y="0.0" time="1177532755009" x="313.0" y="264.0"/>
    <point id="c989d87a-1a87-4412-90c3-33a253df95a8" pressure="0.0"
        tilt_x="0.0" tilt_y="0.0" time="1177532755009" x="318.0" y="263.0"/>
    <point id="eb2ac652-0c07-4afc-8014-430cbeba4303" pressure="0.0"
        tilt_x="0.0" tilt_y="0.0" time="1177532755024" x="304.0" y="268.0"/>
    <point id="32c4cfa4-f192-44a3-96c1-a4826b02dd3f" pressure="0.0"
        tilt_x="0.0" tilt_y="0.0" time="1177532755024" x="309.0" y="266.0"/>
    <point id="28c71924-82b9-48fe-928f-675f6009e4da" pressure="0.0"
        tilt_x="0.0" tilt_y="0.0" time="1177532755040" x="297.0" y="273.0"/>
    <point id="e508bce9-cc30-4ef8-881c-be6fdb932c88" pressure="0.0"
        tilt_x="0.0" tilt_y="0.0" time="1177532755040" x="300.0" y="270.0"/>
    <point id="e86f0c1c-9751-473b-9b2b-32a9e874ff8e" pressure="0.0"
        tilt_x="0.0" tilt_y="0.0" time="1177532755056" x="293.0" y="280.0"/>
    <point id="9f5c7248-ee00-45ae-a25f-afdc02dc274a" pressure="0.0"
        tilt_x="0.0" tilt_y="0.0" time="1177532755056" x="295.0" y="276.0"/>
    <point id="36dbb45f-651c-4a36-acc7-ed1a07cb18cf" pressure="0.0"
        tilt_x="0.0" tilt_y="0.0" time="1177532755071" x="292.0" y="284.0"/>
    <point id="6acabeaa-83c4-43a0-ba5f-d27cb428fa41" pressure="0.0"
        tilt_x="0.0" tilt_y="0.0" time="1177532755087" x="291.0" y="288.0"/>
    <point id="72f5d57b-58db-4e38-be51-4c44516e06e5" pressure="0.0"
        tilt_x="0.0" tilt_y="0.0" time="1177532755087" x="291.0" y="292.0"/>
    <point id="a3af5553-1b2f-4f35-9533-954213cc5447" pressure="0.0"
        tilt_x="0.0" tilt_y="0.0" time="1177532755103" x="291.0" y="297.0"/>
    <point id="e30794fa-8799-490e-ad2d-0e4ded2a5d45" pressure="0.0"
        tilt_x="0.0" tilt_y="0.0" time="1177532755118" x="292.0" y="301.0"/>
    <point id="ccefee4e-076a-426d-95b2-ca3ff2bdec4c" pressure="0.0"
        tilt_x="0.0" tilt_y="0.0" time="1177532755118" x="293.0" y="306.0"/>
    <point id="a238be60-4653-4051-a183-f387a25200ec" pressure="0.0"
        tilt_x="0.0" tilt_y="0.0" time="1177532755134" x="294.0" y="311.0"/>
    <point id="e66844d6-47cc-4c94-b01b-dcaee9093ba0" pressure="0.0"
        tilt_x="0.0" tilt_y="0.0" time="1177532755134" x="296.0" y="316.0"/>
    <point id="db111ed4-29d8-4d9c-9e6f-cb475cf5261b" pressure="0.0"
        tilt_x="0.0" tilt_y="0.0" time="1177532755149" x="299.0" y="321.0"/>
    <point id="d6cb9a07-fe3e-4898-a149-75bc9af6fb0c" pressure="0.0"
        tilt_x="0.0" tilt_y="0.0" time="1177532755149" x="302.0" y="326.0"/>
    <point id="04559a04-6650-4f01-972f-11e4f0b3459b" pressure="0.0"
        tilt_x="0.0" tilt_y="0.0" time="1177532755165" x="305.0" y="330.0"/>
    <point id="c31f6598-d53a-42c8-a07b-400111c41d58" pressure="0.0"
        tilt_x="0.0" tilt_y="0.0" time="1177532755165" x="309.0" y="334.0"/>
    <point id="240cb370-3b05-4f20-a23e-df1d91095f1b" pressure="0.0"
        tilt_x="0.0" tilt_y="0.0" time="1177532755181" x="313.0" y="338.0"/>
    <point id="6b032043-daf4-4371-a046-332a427dfa83" pressure="0.0"
        tilt_x="0.0" tilt_y="0.0" time="1177532755196" x="317.0" y="342.0"/>
    <point id="bd0ea75a-3195-49f0-8f5a-5a91c2ea3e1b" pressure="0.0"
        tilt_x="0.0" tilt_y="0.0" time="1177532755196" x="321.0" y="345.0"/>
    <point id="a09c4022-aa30-480c-bbfb-63335f193fed" pressure="0.0"
        tilt_x="0.0" tilt_y="0.0" time="1177532755212" x="326.0" y="348.0"/>
    <point id="f8e5158a-1a1e-4692-8c7a-2e0cad8fdb92" pressure="0.0"
        tilt_x="0.0" tilt_y="0.0" time="1177532755212" x="332.0" y="350.0"/>
    <point id="b0432c52-dec4-45d5-a072-aeb1e16db4a5" pressure="0.0"
        tilt_x="0.0" tilt_y="0.0" time="1177532755228" x="337.0" y="352.0"/>
    <point id="4a3c5882-feec-47d5-804f-4506ca38e9fa" pressure="0.0"
        tilt_x="0.0" tilt_y="0.0" time="1177532755243" x="343.0" y="352.0"/>
    <point id="16f903a2-2d05-4f1b-9cff-fe41a9a13256" pressure="0.0"
        tilt_x="0.0" tilt_y="0.0" time="1177532755243" x="349.0" y="352.0"/>
    <point id="69d5bbae-8186-4eff-9937-c5d7b824ecda" pressure="0.0"
        tilt_x="0.0" tilt_y="0.0" time="1177532755259" x="355.0" y="352.0"/>
    <point id="7db1f02a-d2f1-4738-bb38-608d34543ce7" pressure="0.0"
        tilt_x="0.0" tilt_y="0.0" time="1177532755259" x="361.0" y="351.0"/>
    <point id="f1571c09-0c8f-4ff9-bc84-553debce8ebe" pressure="0.0"
        tilt_x="0.0" tilt_y="0.0" time="1177532755274" x="367.0" y="349.0"/>
    <point id="dbd2a04c-cbc3-4a39-9707-e02d31942ed9" pressure="0.0"
        tilt_x="0.0" tilt_y="0.0" time="1177532755274" x="373.0" y="347.0"/>
    <point id="5ecc2a13-9ea7-4042-9b59-34984aa575b5" pressure="0.0"
        tilt_x="0.0" tilt_y="0.0" time="1177532755290" x="379.0" y="345.0"/>
    <point id="c0f29840-cc55-4786-8066-caad654536a9" pressure="0.0"
        tilt_x="0.0" tilt_y="0.0" time="1177532755290" x="384.0" y="342.0"/>
    <point id="c9d448a5-fb09-41af-9ac5-e178f6e26e8e" pressure="0.0"
        tilt_x="0.0" tilt_y="0.0" time="1177532755306" x="390.0" y="339.0"/>
    <point id="21f156fe-b24d-4760-8d20-bdaad229d985" pressure="0.0"
        tilt_x="0.0" tilt_y="0.0" time="1177532755321" x="394.0" y="335.0"/>
    <point id="75bd747a-cf8c-4693-a2d3-4c11d65382c0" pressure="0.0"
        tilt_x="0.0" tilt_y="0.0" time="1177532755321" x="397.0" y="332.0"/>
    <point id="a3444e9e-bf5d-4f34-b9f0-e4f9e2f1c5fd" pressure="0.0"
        tilt_x="0.0" tilt_y="0.0" time="1177532755337" x="399.0" y="328.0"/>
    <point id="14838562-5e41-4bfe-b57c-d63d21c217d8" pressure="0.0"
        tilt_x="0.0" tilt_y="0.0" time="1177532755337" x="400.0" y="325.0"/>
    <point id="5168d0c2-ee07-467a-9f84-282fa3ef1139" pressure="0.0"
        tilt_x="0.0" tilt_y="0.0" time="1177532755353" x="399.0" y="320.0"/>
    <point id="4d9e2211-816b-4e34-bf02-8bd1401b26d1" pressure="0.0"
        tilt_x="0.0" tilt_y="0.0" time="1177532755353" x="400.0" y="322.0"/>
    <point id="82e04730-faf7-4159-a5ba-e74f15168110" pressure="0.0"
        tilt_x="0.0" tilt_y="0.0" time="1177532755368" x="396.0" y="316.0"/>
    <point id="92c78693-de1c-4cd4-9ff2-dce1e3f6ff93" pressure="0.0"
        tilt_x="0.0" tilt_y="0.0" time="1177532755368" x="397.0" y="318.0"/>
    <point id="ee411fcc-4075-4985-b021-cbe022e7968d" pressure="0.0"
        tilt_x="0.0" tilt_y="0.0" time="1177532755384" x="395.0" y="315.0"/>
    <point id="a48f4295-8792-4e59-88e3-8bd636c60752" pressure="0.0"
        tilt_x="0.0" tilt_y="0.0" time="1177532755399" x="395.0" y="314.0"/>
    <stroke id="12e1413a-948d-43a8-8e29-7654617da72f" label="Complex" visible="true">
        <arg type="point">bd58b928-983f-4dba-91d6-cacff471ceef</arg>
        <arg type="point">241e6f0c-2064-4de4-adcf-9245dd2759c0</arg>
        <arg type="point">b6c1c7ff-f7ea-438a-95d8-f23459d03b18</arg>
        <arg type="point">bef89d23-d679-43a6-9c4a-837c03fa4a36</arg>
        <arg type="point">efaa0dc0-77dd-4c30-be9a-1e1330c20d0a</arg>
        <arg type="point">3889d5a7-51cb-4751-81ee-e413f0359146</arg>
        <arg type="point">08372411-5a63-4f1d-85a7-16d18f72fb9b</arg>
        <arg type="point">ce8ce067-d149-45f3-a398-1c133ba65e80</arg>
        <arg type="point">60fd5f26-e2f2-450c-8a1b-04101159ca45</arg>
        <arg type="point">093dac45-57ff-4ea3-b059-aa5b77f5efaf</arg>
        <arg type="point">c0fbe4a1-6dac-4af2-a500-87a2f2d55432</arg>
        <arg type="point">6bc639ab-9108-47f4-97ff-c21d96e56663</arg>
        <arg type="point">f787b360-904a-464c-8057-fac5258f97ab</arg>
        <arg type="point">dc8eab5a-fdab-46a1-ac94-f4b6552d7d22</arg>
        <arg type="point">95285c39-0baf-4339-87dd-afc53defaad7</arg>
        <arg type="point">a59f43a4-8599-4073-bd2e-fb5c52659c19</arg>
        <arg type="point">0409627e-0daa-4973-9cf3-68dd5c0ff1c9</arg>
        <arg type="point">0e30579d-ffe6-4023-9a61-55798a5e9b33</arg>
        <arg type="point">cf92a225-cd93-4d23-97d2-5687933ee32a</arg>
        <arg type="point">5feaff76-3998-4644-ac4c-f0f785a0be7d</arg>
        <arg type="point">eb563912-ca64-4e06-ba44-93151469d11e</arg>
        <arg type="point">eb0398b3-3d70-4e11-ab5d-33b68642201e</arg>
        <arg type="point">fd2e1caa-504d-4e80-89b6-9c2af748e5f8</arg>
        <arg type="point">46c80363-bc60-40d8-a96a-bb09527b0c24</arg>
        <arg type="point">6320171a-dbe5-4a30-ba27-a22cc0ee4373</arg>
        <arg type="point">d4440982-5c17-4dc1-9dc2-c5f8cce2a625</arg>
        <arg type="point">acb10c7d-fb4b-4551-b197-044515544a6a</arg>
        <arg type="point">e9b2227f-07e3-4a5b-af2e-fb226426106a</arg>
        <arg type="point">5546ef2a-e041-4a1d-bc10-2ef8374ff482</arg>
        <arg type="point">f478814a-4120-4fc1-b1cb-63d9b9d5bc7d</arg>
        <arg type="point">c5e85a10-453e-4990-8502-e46e9af01c5b</arg>
        <arg type="point">5801ada9-e9b1-456a-9e95-3f7500b30b21</arg>
        <arg type="point">bdcd7bae-a265-4d9d-a24f-5e61f44deb36</arg>
        <arg type="point">4d0aa280-2a5f-4971-a232-9eddff985dff</arg>
        <arg type="point">45e3ca54-2e71-453c-af1f-000afd161129</arg>
        <arg type="point">d66f8375-d6d8-4451-a526-3ff80bcc94a2</arg>
        <arg type="point">eba538fd-5d7a-4db2-b910-8246603ea536</arg>
        <arg type="point">a6fbba50-f49c-40a9-b71f-df663617032e</arg>
        <arg type="point">f0374d34-1e22-4a22-94d0-11581af6976d</arg>
        <arg type="point">ec089bf3-dffd-45b4-8d66-b26176e190a8</arg>
        <arg type="point">7723f1fb-ba8f-4df4-818a-c8015ed0fb0a</arg>
        <arg type="point">b983fe3c-c525-4497-98b6-73d861a89618</arg>
        <arg type="point">6572729b-02cd-4ae1-bebb-254c811301f8</arg>
        <arg type="point">ccf57056-d2ab-4e7a-b14f-c58e930f0efb</arg>
        <arg type="point">032c62b4-2719-4762-800d-e198cf74f5f0</arg>
        <arg type="point">2664fd79-9ced-4465-b9f8-294881d8d939</arg>
        <arg type="point">5b985c6d-4782-4e76-b89d-315b73e2e4ce</arg>
        <arg type="point">b0fddc0d-8438-405e-a5ff-4a47b895d3c5</arg>
        <arg type="point">e444ea9a-e2a9-4bbb-a97d-0fc30769a5df</arg>
        <arg type="point">8a80e613-9163-4d9f-96cb-8b050b7bcfc9</arg>
        <arg type="point">ee3fd76c-4cc4-42ac-99d4-455d4525c5bd</arg>
        <arg type="point">e007a7a6-a073-4d8a-8214-f3c1803b6c2e</arg>
        <arg type="point">dd823a99-54fe-4350-af7e-c10681ea6a86</arg>
        <arg type="point">e056e479-db25-417e-a1e9-09b9e40b2496</arg>
        <arg type="point">d453d253-e757-48f4-af98-7049fbaa1030</arg>
        <arg type="point">bb9ad587-41e4-4933-9f9c-34a384bdcace</arg>
        <arg type="point">32fa8b92-a170-41e1-b753-2afdc605064a</arg>
        <arg type="point">c989d87a-1a87-4412-90c3-33a253df95a8</arg>
        <arg type="point">f1ca70c1-8ab5-4de3-bf55-6f513faeeb80</arg>
        <arg type="point">32c4cfa4-f192-44a3-96c1-a4826b02dd3f</arg>
        <arg type="point">eb2ac652-0c07-4afc-8014-430cbeba4303</arg>
        <arg type="point">e508bce9-cc30-4ef8-881c-be6fdb932c88</arg>
        <arg type="point">28c71924-82b9-48fe-928f-675f6009e4da</arg>
        <arg type="point">9f5c7248-ee00-45ae-a25f-afdc02dc274a</arg>
        <arg type="point">e86f0c1c-9751-473b-9b2b-32a9e874ff8e</arg>
        <arg type="point">36dbb45f-651c-4a36-acc7-ed1a07cb18cf</arg>
        <arg type="point">6acabeaa-83c4-43a0-ba5f-d27cb428fa41</arg>
        <arg type="point">72f5d57b-58db-4e38-be51-4c44516e06e5</arg>
        <arg type="point">a3af5553-1b2f-4f35-9533-954213cc5447</arg>
        <arg type="point">e30794fa-8799-490e-ad2d-0e4ded2a5d45</arg>
        <arg type="point">ccefee4e-076a-426d-95b2-ca3ff2bdec4c</arg>
        <arg type="point">a238be60-4653-4051-a183-f387a25200ec</arg>
        <arg type="point">e66844d6-47cc-4c94-b01b-dcaee9093ba0</arg>
        <arg type="point">db111ed4-29d8-4d9c-9e6f-cb475cf5261b</arg>
        <arg type="point">d6cb9a07-fe3e-4898-a149-75bc9af6fb0c</arg>
        <arg type="point">04559a04-6650-4f01-972f-11e4f0b3459b</arg>
        <arg type="point">c31f6598-d53a-42c8-a07b-400111c41d58</arg>
        <arg type="point">240cb370-3b05-4f20-a23e-df1d91095f1b</arg>
        <arg type="point">6b032043-daf4-4371-a046-332a427dfa83</arg>
        <arg type="point">bd0ea75a-3195-49f0-8f5a-5a91c2ea3e1b</arg>
        <arg type="point">a09c4022-aa30-480c-bbfb-63335f193fed</arg>
        <arg type="point">f8e5158a-1a1e-4692-8c7a-2e0cad8fdb92</arg>
        <arg type="point">b0432c52-dec4-45d5-a072-aeb1e16db4a5</arg>
        <arg type="point">4a3c5882-feec-47d5-804f-4506ca38e9fa</arg>
        <arg type="point">16f903a2-2d05-4f1b-9cff-fe41a9a13256</arg>
        <arg type="point">69d5bbae-8186-4eff-9937-c5d7b824ecda</arg>
        <arg type="point">7db1f02a-d2f1-4738-bb38-608d34543ce7</arg>
        <arg type="point">f1571c09-0c8f-4ff9-bc84-553debce8ebe</arg>
        <arg type="point">dbd2a04c-cbc3-4a39-9707-e02d31942ed9</arg>
        <arg type="point">5ecc2a13-9ea7-4042-9b59-34984aa575b5</arg>
        <arg type="point">c0f29840-cc55-4786-8066-caad654536a9</arg>
        <arg type="point">c9d448a5-fb09-41af-9ac5-e178f6e26e8e</arg>
        <arg type="point">21f156fe-b24d-4760-8d20-bdaad229d985</arg>
        <arg type="point">75bd747a-cf8c-4693-a2d3-4c11d65382c0</arg>
        <arg type="point">a3444e9e-bf5d-4f34-b9f0-e4f9e2f1c5fd</arg>
        <arg type="point">14838562-5e41-4bfe-b57c-d63d21c217d8</arg>
        <arg type="point">4d9e2211-816b-4e34-bf02-8bd1401b26d1</arg>
        <arg type="point">5168d0c2-ee07-467a-9f84-282fa3ef1139</arg>
        <arg type="point">92c78693-de1c-4cd4-9ff2-dce1e3f6ff93</arg>
        <arg type="point">82e04730-faf7-4159-a5ba-e74f15168110</arg>
        <arg type="point">ee411fcc-4075-4985-b021-cbe022e7968d</arg>
        <arg type="point">a48f4295-8792-4e59-88e3-8bd636c60752</arg>
    </stroke>
</sketch>
