<?xml version="1.0" encoding="UTF-8"?>
<sketch id="303fadb2-5d9d-498c-8293-88c4965522aa" type="SRL">
    <point id="440dfcd6-95ae-4dc5-bb63-c099cd82f755" pressure="0.0"
        tilt_x="0.0" tilt_y="0.0" time="1177610526890" x="219.0" y="341.0"/>
    <point id="de19263c-7569-4de9-9b68-98990f48edc6" pressure="0.0"
        tilt_x="0.0" tilt_y="0.0" time="1177610526906" x="219.0" y="342.0"/>
    <point id="0c9c1ce8-62a9-42b9-9b46-0acc249fcda5" pressure="0.0"
        tilt_x="0.0" tilt_y="0.0" time="1177610526937" x="220.0" y="342.0"/>
    <point id="5714992b-1dba-4a04-8939-111f0c3f2677" pressure="0.0"
        tilt_x="0.0" tilt_y="0.0" time="1177610526952" x="221.0" y="341.0"/>
    <point id="96b84a38-9cb7-4fc6-a380-dfaa76a8e0a9" pressure="0.0"
        tilt_x="0.0" tilt_y="0.0" time="1177610526952" x="222.0" y="339.0"/>
    <point id="68ab61be-7e1b-41be-b9eb-1ae5cdaa8b7d" pressure="0.0"
        tilt_x="0.0" tilt_y="0.0" time="1177610526968" x="224.0" y="337.0"/>
    <point id="0bf69ffe-30dc-4e68-a621-2f8351d296c1" pressure="0.0"
        tilt_x="0.0" tilt_y="0.0" time="1177610526984" x="227.0" y="334.0"/>
    <point id="a239006d-2e79-4d47-91a7-7baf381b32c2" pressure="0.0"
        tilt_x="0.0" tilt_y="0.0" time="1177610526984" x="230.0" y="330.0"/>
    <point id="e1fd14ab-f5e9-4c85-8628-8b4e75a26176" pressure="0.0"
        tilt_x="0.0" tilt_y="0.0" time="1177610526999" x="234.0" y="326.0"/>
    <point id="8ab5cd03-648d-46ca-8ea9-423dd57ec3c1" pressure="0.0"
        tilt_x="0.0" tilt_y="0.0" time="1177610526999" x="238.0" y="320.0"/>
    <point id="e27f0ac7-eeb6-4aa9-9a61-f6828643a4bf" pressure="0.0"
        tilt_x="0.0" tilt_y="0.0" time="1177610527015" x="243.0" y="314.0"/>
    <point id="b1bcb95b-2e3c-47e0-912f-deb58964e18f" pressure="0.0"
        tilt_x="0.0" tilt_y="0.0" time="1177610527015" x="248.0" y="308.0"/>
    <point id="ce392f6a-cdce-43b5-b38b-ad6c6a1f2840" pressure="0.0"
        tilt_x="0.0" tilt_y="0.0" time="1177610527031" x="254.0" y="301.0"/>
    <point id="50217bd9-5712-4147-b72c-659a94080a86" pressure="0.0"
        tilt_x="0.0" tilt_y="0.0" time="1177610527031" x="260.0" y="294.0"/>
    <point id="43cf86cf-53c2-46e3-aba1-41fce733c2e1" pressure="0.0"
        tilt_x="0.0" tilt_y="0.0" time="1177610527046" x="267.0" y="286.0"/>
    <point id="9bf7a737-0062-48fa-afc3-845e5b0a1591" pressure="0.0"
        tilt_x="0.0" tilt_y="0.0" time="1177610527062" x="274.0" y="278.0"/>
    <point id="dd45a57f-a78c-4326-939d-039e5531cb0e" pressure="0.0"
        tilt_x="0.0" tilt_y="0.0" time="1177610527062" x="281.0" y="270.0"/>
    <point id="018afe03-f34b-4507-8d80-61aafc33bc09" pressure="0.0"
        tilt_x="0.0" tilt_y="0.0" time="1177610527077" x="289.0" y="261.0"/>
    <point id="33c77968-f27a-455b-8c5f-e3e63e8b40db" pressure="0.0"
        tilt_x="0.0" tilt_y="0.0" time="1177610527077" x="296.0" y="252.0"/>
    <point id="c266e4ea-605c-4796-be4b-531ad41501db" pressure="0.0"
        tilt_x="0.0" tilt_y="0.0" time="1177610527093" x="304.0" y="244.0"/>
    <point id="557ff576-e759-45aa-a503-d6b17859b88a" pressure="0.0"
        tilt_x="0.0" tilt_y="0.0" time="1177610527093" x="311.0" y="236.0"/>
    <point id="1d59d4a2-2b41-43ee-9e5e-7bbd99d37f10" pressure="0.0"
        tilt_x="0.0" tilt_y="0.0" time="1177610527109" x="318.0" y="229.0"/>
    <point id="638bbe0e-5075-42ef-ad6e-1f04b5b12156" pressure="0.0"
        tilt_x="0.0" tilt_y="0.0" time="1177610527109" x="325.0" y="222.0"/>
    <point id="bdfdda0a-ba1c-4a8a-a6b8-7f079f062e5e" pressure="0.0"
        tilt_x="0.0" tilt_y="0.0" time="1177610527124" x="331.0" y="216.0"/>
    <point id="abf877e2-22a3-4bbb-a2a6-739e99d62a45" pressure="0.0"
        tilt_x="0.0" tilt_y="0.0" time="1177610527140" x="336.0" y="211.0"/>
    <point id="3c6668b3-9f58-4740-b012-74793c25f8fa" pressure="0.0"
        tilt_x="0.0" tilt_y="0.0" time="1177610527140" x="340.0" y="206.0"/>
    <point id="642835a8-0f0a-45f6-9d9a-931fce3a91c8" pressure="0.0"
        tilt_x="0.0" tilt_y="0.0" time="1177610527156" x="344.0" y="202.0"/>
    <point id="13461a2b-4ded-41ef-abd3-001df2c21a98" pressure="0.0"
        tilt_x="0.0" tilt_y="0.0" time="1177610527156" x="348.0" y="198.0"/>
    <point id="e19fbb79-1d51-49b2-a6de-f13ee73d380b" pressure="0.0"
        tilt_x="0.0" tilt_y="0.0" time="1177610527171" x="351.0" y="195.0"/>
    <point id="44470b55-517b-4643-bcbd-95771949854d" pressure="0.0"
        tilt_x="0.0" tilt_y="0.0" time="1177610527187" x="354.0" y="193.0"/>
    <point id="9b12418a-c07e-451e-a644-39d369f90129" pressure="0.0"
        tilt_x="0.0" tilt_y="0.0" time="1177610527187" x="356.0" y="191.0"/>
    <point id="95319813-c807-4347-8a4a-0e0bae75c4f8" pressure="0.0"
        tilt_x="0.0" tilt_y="0.0" time="1177610527202" x="358.0" y="190.0"/>
    <point id="d33dd8bf-4416-4682-b2b4-df409c1261c1" pressure="0.0"
        tilt_x="0.0" tilt_y="0.0" time="1177610527202" x="359.0" y="189.0"/>
    <point id="ba22161f-d66d-46e7-aaf0-b62628aabd17" pressure="0.0"
        tilt_x="0.0" tilt_y="0.0" time="1177610527218" x="360.0" y="188.0"/>
    <point id="996b5221-65e8-435c-9031-0556a8b3d2f0" pressure="0.0"
        tilt_x="0.0" tilt_y="0.0" time="1177610527218" x="360.0" y="189.0"/>
    <point id="7ba38a04-de2e-439d-809f-4ec022c9d499" pressure="0.0"
        tilt_x="0.0" tilt_y="0.0" time="1177610527234" x="360.0" y="189.0"/>
    <point id="72791835-bf1f-4635-a1ca-8feab5865822" pressure="0.0"
        tilt_x="0.0" tilt_y="0.0" time="1177610527249" x="360.0" y="190.0"/>
    <point id="750021dc-b3cf-4d79-8b13-7d560674da23" pressure="0.0"
        tilt_x="0.0" tilt_y="0.0" time="1177610527265" x="359.0" y="192.0"/>
    <point id="35551155-30e2-4c55-8563-76a43670cf1e" pressure="0.0"
        tilt_x="0.0" tilt_y="0.0" time="1177610527265" x="360.0" y="191.0"/>
    <point id="c529bbae-92a3-4d6f-9f0f-a2a1871761cb" pressure="0.0"
        tilt_x="0.0" tilt_y="0.0" time="1177610527281" x="358.0" y="196.0"/>
    <point id="ea83b59a-ac16-4f35-bbd4-a09007db5cb5" pressure="0.0"
        tilt_x="0.0" tilt_y="0.0" time="1177610527281" x="359.0" y="194.0"/>
    <point id="02d40b74-9e9a-4657-9324-44da5a8dc188" pressure="0.0"
        tilt_x="0.0" tilt_y="0.0" time="1177610527296" x="358.0" y="199.0"/>
    <point id="53bc49f6-9e2b-49e8-b2e7-a0fa7bf5f614" pressure="0.0"
        tilt_x="0.0" tilt_y="0.0" time="1177610527312" x="355.0" y="207.0"/>
    <point id="89630a8c-045b-4ddb-a3ba-8a27b50dc0cb" pressure="0.0"
        tilt_x="0.0" tilt_y="0.0" time="1177610527312" x="357.0" y="203.0"/>
    <point id="dc544177-9719-47e2-852a-a63e3420228d" pressure="0.0"
        tilt_x="0.0" tilt_y="0.0" time="1177610527327" x="352.0" y="217.0"/>
    <point id="36449f50-248d-4eff-960d-c16e2be49202" pressure="0.0"
        tilt_x="0.0" tilt_y="0.0" time="1177610527327" x="354.0" y="212.0"/>
    <point id="0e52d908-8ce7-4a24-b231-94e37c298f24" pressure="0.0"
        tilt_x="0.0" tilt_y="0.0" time="1177610527343" x="347.0" y="229.0"/>
    <point id="c9c1c7b1-09cf-4048-99ed-97f550617378" pressure="0.0"
        tilt_x="0.0" tilt_y="0.0" time="1177610527343" x="350.0" y="222.0"/>
    <point id="cba18f06-dc5a-4417-8522-9ae11eed767f" pressure="0.0"
        tilt_x="0.0" tilt_y="0.0" time="1177610527359" x="344.0" y="235.0"/>
    <point id="5c0c4128-b508-436f-af3a-3bd032962d49" pressure="0.0"
        tilt_x="0.0" tilt_y="0.0" time="1177610527374" x="338.0" y="250.0"/>
    <point id="35947ed7-6576-4810-9963-d3f6809b036a" pressure="0.0"
        tilt_x="0.0" tilt_y="0.0" time="1177610527374" x="341.0" y="243.0"/>
    <point id="8adf0636-fb19-4bb0-ae7e-fe11e3e1c3c5" pressure="0.0"
        tilt_x="0.0" tilt_y="0.0" time="1177610527390" x="333.0" y="262.0"/>
    <point id="4e11966a-7ca7-4677-a7d6-72281441837d" pressure="0.0"
        tilt_x="0.0" tilt_y="0.0" time="1177610527390" x="336.0" y="256.0"/>
    <point id="b0eac74b-ab61-49d5-9808-6d64b57d7a3e" pressure="0.0"
        tilt_x="0.0" tilt_y="0.0" time="1177610527406" x="330.0" y="273.0"/>
    <point id="2bb03dfe-3fa9-4fda-9106-eada8825792a" pressure="0.0"
        tilt_x="0.0" tilt_y="0.0" time="1177610527406" x="331.0" y="268.0"/>
    <stroke id="fb86bd52-b70a-4364-bdac-700c6a6d67c4" label="Polyline" visible="true">
        <arg type="point">440dfcd6-95ae-4dc5-bb63-c099cd82f755</arg>
        <arg type="point">de19263c-7569-4de9-9b68-98990f48edc6</arg>
        <arg type="point">0c9c1ce8-62a9-42b9-9b46-0acc249fcda5</arg>
        <arg type="point">5714992b-1dba-4a04-8939-111f0c3f2677</arg>
        <arg type="point">96b84a38-9cb7-4fc6-a380-dfaa76a8e0a9</arg>
        <arg type="point">68ab61be-7e1b-41be-b9eb-1ae5cdaa8b7d</arg>
        <arg type="point">0bf69ffe-30dc-4e68-a621-2f8351d296c1</arg>
        <arg type="point">a239006d-2e79-4d47-91a7-7baf381b32c2</arg>
        <arg type="point">e1fd14ab-f5e9-4c85-8628-8b4e75a26176</arg>
        <arg type="point">8ab5cd03-648d-46ca-8ea9-423dd57ec3c1</arg>
        <arg type="point">e27f0ac7-eeb6-4aa9-9a61-f6828643a4bf</arg>
        <arg type="point">b1bcb95b-2e3c-47e0-912f-deb58964e18f</arg>
        <arg type="point">ce392f6a-cdce-43b5-b38b-ad6c6a1f2840</arg>
        <arg type="point">50217bd9-5712-4147-b72c-659a94080a86</arg>
        <arg type="point">43cf86cf-53c2-46e3-aba1-41fce733c2e1</arg>
        <arg type="point">9bf7a737-0062-48fa-afc3-845e5b0a1591</arg>
        <arg type="point">dd45a57f-a78c-4326-939d-039e5531cb0e</arg>
        <arg type="point">018afe03-f34b-4507-8d80-61aafc33bc09</arg>
        <arg type="point">33c77968-f27a-455b-8c5f-e3e63e8b40db</arg>
        <arg type="point">c266e4ea-605c-4796-be4b-531ad41501db</arg>
        <arg type="point">557ff576-e759-45aa-a503-d6b17859b88a</arg>
        <arg type="point">1d59d4a2-2b41-43ee-9e5e-7bbd99d37f10</arg>
        <arg type="point">638bbe0e-5075-42ef-ad6e-1f04b5b12156</arg>
        <arg type="point">bdfdda0a-ba1c-4a8a-a6b8-7f079f062e5e</arg>
        <arg type="point">abf877e2-22a3-4bbb-a2a6-739e99d62a45</arg>
        <arg type="point">3c6668b3-9f58-4740-b012-74793c25f8fa</arg>
        <arg type="point">642835a8-0f0a-45f6-9d9a-931fce3a91c8</arg>
        <arg type="point">13461a2b-4ded-41ef-abd3-001df2c21a98</arg>
        <arg type="point">e19fbb79-1d51-49b2-a6de-f13ee73d380b</arg>
        <arg type="point">44470b55-517b-4643-bcbd-95771949854d</arg>
        <arg type="point">9b12418a-c07e-451e-a644-39d369f90129</arg>
        <arg type="point">95319813-c807-4347-8a4a-0e0bae75c4f8</arg>
        <arg type="point">d33dd8bf-4416-4682-b2b4-df409c1261c1</arg>
        <arg type="point">996b5221-65e8-435c-9031-0556a8b3d2f0</arg>
        <arg type="point">ba22161f-d66d-46e7-aaf0-b62628aabd17</arg>
        <arg type="point">7ba38a04-de2e-439d-809f-4ec022c9d499</arg>
        <arg type="point">72791835-bf1f-4635-a1ca-8feab5865822</arg>
        <arg type="point">35551155-30e2-4c55-8563-76a43670cf1e</arg>
        <arg type="point">750021dc-b3cf-4d79-8b13-7d560674da23</arg>
        <arg type="point">ea83b59a-ac16-4f35-bbd4-a09007db5cb5</arg>
        <arg type="point">c529bbae-92a3-4d6f-9f0f-a2a1871761cb</arg>
        <arg type="point">02d40b74-9e9a-4657-9324-44da5a8dc188</arg>
        <arg type="point">89630a8c-045b-4ddb-a3ba-8a27b50dc0cb</arg>
        <arg type="point">53bc49f6-9e2b-49e8-b2e7-a0fa7bf5f614</arg>
        <arg type="point">36449f50-248d-4eff-960d-c16e2be49202</arg>
        <arg type="point">dc544177-9719-47e2-852a-a63e3420228d</arg>
        <arg type="point">c9c1c7b1-09cf-4048-99ed-97f550617378</arg>
        <arg type="point">0e52d908-8ce7-4a24-b231-94e37c298f24</arg>
        <arg type="point">cba18f06-dc5a-4417-8522-9ae11eed767f</arg>
        <arg type="point">35947ed7-6576-4810-9963-d3f6809b036a</arg>
        <arg type="point">5c0c4128-b508-436f-af3a-3bd032962d49</arg>
        <arg type="point">4e11966a-7ca7-4677-a7d6-72281441837d</arg>
        <arg type="point">8adf0636-fb19-4bb0-ae7e-fe11e3e1c3c5</arg>
        <arg type="point">2bb03dfe-3fa9-4fda-9106-eada8825792a</arg>
        <arg type="point">b0eac74b-ab61-49d5-9808-6d64b57d7a3e</arg>
    </stroke>
</sketch>
